AUTHORS
CHANGES.rst
LICENSE
MANIFEST.in
README.rst
setup.cfg
setup.py
block_diag_ilu/__init__.py
block_diag_ilu/_block_diag_ilu.cpp
block_diag_ilu/_config.py
block_diag_ilu/_release.py
block_diag_ilu/datastruct.py
block_diag_ilu.egg-info/PKG-INFO
block_diag_ilu.egg-info/SOURCES.txt
block_diag_ilu.egg-info/dependency_links.txt
block_diag_ilu.egg-info/requires.txt
block_diag_ilu.egg-info/top_level.txt
block_diag_ilu/include/block_diag_ilu.hpp
block_diag_ilu/include/block_diag_ilu.pxd
block_diag_ilu/tests/__init__.py
block_diag_ilu/tests/test_block_diag_ilu.py