Metadata-Version: 1.1
Name: block-diag-ilu
Version: 0.4.6
Summary: block_diag_ilu is a C++ implementation of an incomplete LU factorization, ILU(0).
Home-page: https://github.com/chemreac/block_diag_ilu
Author: Bjoern I. Dahlgren
Author-email: bjodah@gmail.com
License: BSD
Platform: UNKNOWN
Classifier: Development Status :: 4 - Beta
Classifier: License :: OSI Approved :: BSD License
Classifier: Operating System :: OS Independent
Classifier: Topic :: Scientific/Engineering
Classifier: Topic :: Scientific/Engineering :: Mathematics
